{
  "info": {
    "_dirName": "info",
    "_dirType": "sub",
    "version": {
      "_dirName": "version",
      "_dirType": "int",
      "_value": 10
    },
    "cloud": {
      "_dirName": "cloud",
      "_dirType": "int",
      "_value": 0
    },
    "town": {
      "_dirName": "town",
      "_dirType": "int",
      "_value": 0
    },
    "swim": {
      "_dirName": "swim",
      "_dirType": "int",
      "_value": 0
    },
    "returnMap": {
      "_dirName": "returnMap",
      "_dirType": "int",
      "_value": 970050020
    },
    "forcedReturn": {
      "_dirName": "forcedReturn",
      "_dirType": "int",
      "_value": 970050020
    },
    "mobRate": {
      "_dirName": "mobRate",
      "_dirType": "float",
      "_value": "1.0"
    },
    "bgm": {
      "_dirName": "bgm",
      "_dirType": "string",
      "_value": "Bgm00/GoPicnic"
    },
    "onFirstUserEnter": {
      "_dirName": "onFirstUserEnter",
      "_dirType": "string",
      "_value": ""
    },
    "onUserEnter": {
      "_dirName": "onUserEnter",
      "_dirType": "string",
      "_value": "Balloon_W_Enter"
    },
    "mapMark": {
      "_dirName": "mapMark",
      "_dirType": "string",
      "_value": "Henesys"
    },
    "fly": {
      "_dirName": "fly",
      "_dirType": "int",
      "_value": 0
    },
    "noMapCmd": {
      "_dirName": "noMapCmd",
      "_dirType": "int",
      "_value": 0
    },
    "hideMinimap": {
      "_dirName": "hideMinimap",
      "_dirType": "int",
      "_value": 1
    },
    "fieldLimit": {
      "_dirName": "fieldLimit",
      "_dirType": "int",
      "_value": 336636
    },
    "link": {
      "_dirName": "link",
      "_dirType": "string",
      "_value": "970050000"
    }
  }
}
