{
  "info": {
    "_dirName": "info",
    "_dirType": "sub",
    "version": {
      "_dirName": "version",
      "_dirType": "int",
      "_value": 10
    },
    "cloud": {
      "_dirName": "cloud",
      "_dirType": "int",
      "_value": 0
    },
    "town": {
      "_dirName": "town",
      "_dirType": "int",
      "_value": 1
    },
    "returnMap": {
      "_dirName": "returnMap",
      "_dirType": "int",
      "_value": 220000000
    },
    "forcedReturn": {
      "_dirName": "forcedReturn",
      "_dirType": "int",
      "_value": 999999999
    },
    "mobRate": {
      "_dirName": "mobRate",
      "_dirType": "float",
      "_value": "1.0"
    },
    "bgm": {
      "_dirName": "bgm",
      "_dirType": "string",
      "_value": "Bgm06/FantasticThinking"
    },
    "mapMark": {
      "_dirName": "mapMark",
      "_dirType": "string",
      "_value": "Ludibrium"
    },
    "hideMinimap": {
      "_dirName": "hideMinimap",
      "_dirType": "int",
      "_value": 0
    },
    "fieldLimit": {
      "_dirName": "fieldLimit",
      "_dirType": "int",
      "_value": 0
    },
    "VRTop": {
      "_dirName": "VRTop",
      "_dirType": "int",
      "_value": -1152
    },
    "VRLeft": {
      "_dirName": "VRLeft",
      "_dirType": "int",
      "_value": -512
    },
    "VRBottom": {
      "_dirName": "VRBottom",
      "_dirType": "int",
      "_value": 384
    },
    "VRRight": {
      "_dirName": "VRRight",
      "_dirType": "int",
      "_value": 512
    }
  },
  "back": {
    "_dirName": "back",
    "_dirType": "sub",
    "0": {
      "_dirName": "0",
      "_dirType": "sub",
      "bS": {
        "_dirName": "bS",
        "_dirType": "string",
        "_value": "toyCastle"
      },
      "front": {
        "_dirName": "front",
        "_dirType": "int",
        "_value": 0
      },
      "ani": {
        "_dirName": "ani",
        "_dirType": "int",
        "_value": 0
      },
      "no": {
        "_dirName": "no",
        "_dirType": "int",
        "_value": 0
      },
      "f": {
        "_dirName": "f",
        "_dirType": "int",
        "_value": 0
      },
      "x": {
        "_dirName": "x",
        "_dirType": "int",
        "_value": 0
      },
      "y": {
        "_dirName": "y",
        "_dirType": "int",
        "_value": 0
      },
      "rx": {
        "_dirName": "rx",
        "_dirType": "int",
        "_value": 0
      },
      "ry": {
        "_dirName": "ry",
        "_dirType": "int",
        "_value": 0
      },
      "type": {
        "_dirName": "type",
        "_dirType": "int",
        "_value": 3
      },
      "cx": {
        "_dirName": "cx",
        "_dirType": "int",
        "_value": 0
      },
      "cy": {
        "_dirName": "cy",
        "_dirType": "int",
        "_value": 0
      },
      "a": {
        "_dirName": "a",
        "_dirType": "int",
        "_value": 255
      }
    },
    "1": {
      "_dirName": "1",
      "_dirType": "sub",
      "bS": {
        "_dirName": "bS",
        "_dirType": "string",
        "_value": "toyCastle"
      },
      "front": {
        "_dirName": "front",
        "_dirType": "int",
        "_value": 0
      },
      "ani": {
        "_dirName": "ani",
        "_dirType": "int",
        "_value": 0
      },
      "no": {
        "_dirName": "no",
        "_dirType": "int",
        "_value": 1
      },
      "f": {
        "_dirName": "f",
        "_dirType": "int",
        "_value": 0
      },
      "x": {
        "_dirName": "x",
        "_dirType": "int",
        "_value": -16
      },
      "y": {
        "_dirName": "y",
        "_dirType": "int",
        "_value": -24
      },
      "rx": {
        "_dirName": "rx",
        "_dirType": "int",
        "_value": -5
      },
      "ry": {
        "_dirName": "ry",
        "_dirType": "int",
        "_value": -100
      },
      "type": {
        "_dirName": "type",
        "_dirType": "int",
        "_value": 1
      },
      "cx": {
        "_dirName": "cx",
        "_dirType": "int",
        "_value": 0
      },
      "cy": {
        "_dirName": "cy",
        "_dirType": "int",
        "_value": 0
      },
      "a": {
        "_dirName": "a",
        "_dirType": "int",
        "_value": 255
      }
    },
    "2": {
      "_dirName": "2",
      "_dirType": "sub",
      "bS": {
        "_dirName": "bS",
        "_dirType": "string",
        "_value": "toyCastle"
      },
      "front": {
        "_dirName": "front",
        "_dirType": "int",
        "_value": 0
      },
      "ani": {
        "_dirName": "ani",
        "_dirType": "int",
        "_value": 0
      },
      "no": {
        "_dirName": "no",
        "_dirType": "int",
        "_value": 15
      },
      "f": {
        "_dirName": "f",
        "_dirType": "int",
        "_value": 0
      },
      "x": {
        "_dirName": "x",
        "_dirType": "int",
        "_value": -230
      },
      "y": {
        "_dirName": "y",
        "_dirType": "int",
        "_value": 115
      },
      "rx": {
        "_dirName": "rx",
        "_dirType": "int",
        "_value": 0
      },
      "ry": {
        "_dirName": "ry",
        "_dirType": "int",
        "_value": -90
      },
      "type": {
        "_dirName": "type",
        "_dirType": "int",
        "_value": 0
      },
      "cx": {
        "_dirName": "cx",
        "_dirType": "int",
        "_value": 0
      },
      "cy": {
        "_dirName": "cy",
        "_dirType": "int",
        "_value": 0
      },
      "a": {
        "_dirName": "a",
        "_dirType": "int",
        "_value": 255
      }
    },
    "3": {
      "_dirName": "3",
      "_dirType": "sub",
      "bS": {
        "_dirName": "bS",
        "_dirType": "string",
        "_value": "toyCastle"
      },
      "front": {
        "_dirName": "front",
        "_dirType": "int",
        "_value": 0
      },
      "ani": {
        "_dirName": "ani",
        "_dirType": "int",
        "_value": 0
      },
      "no": {
        "_dirName": "no",
        "_dirType": "int",
        "_value": 12
      },
      "f": {
        "_dirName": "f",
        "_dirType": "int",
        "_value": 0
      },
      "x": {
        "_dirName": "x",
        "_dirType": "int",
        "_value": -81
      },
      "y": {
        "_dirName": "y",
        "_dirType": "int",
        "_value": -148
      },
      "rx": {
        "_dirName": "rx",
        "_dirType": "int",
        "_value": 3
      },
      "ry": {
        "_dirName": "ry",
        "_dirType": "int",
        "_value": 0
      },
      "type": {
        "_dirName": "type",
        "_dirType": "int",
        "_value": 4
      },
      "cx": {
        "_dirName": "cx",
        "_dirType": "int",
        "_value": 900
      },
      "cy": {
        "_dirName": "cy",
        "_dirType": "int",
        "_value": 0
      },
      "a": {
        "_dirName": "a",
        "_dirType": "int",
        "_value": 255
      }
    },
    "4": {
      "_dirName": "4",
      "_dirType": "sub",
      "bS": {
        "_dirName": "bS",
        "_dirType": "string",
        "_value": "toyCastle"
      },
      "front": {
        "_dirName": "front",
        "_dirType": "int",
        "_value": 0
      },
      "ani": {
        "_dirName": "ani",
        "_dirType": "int",
        "_value": 0
      },
      "no": {
        "_dirName": "no",
        "_dirType": "int",
        "_value": 10
      },
      "f": {
        "_dirName": "f",
        "_dirType": "int",
        "_value": 0
      },
      "x": {
        "_dirName": "x",
        "_dirType": "int",
        "_value": -38
      },
      "y": {
        "_dirName": "y",
        "_dirType": "int",
        "_value": -16
      },
      "rx": {
        "_dirName": "rx",
        "_dirType": "int",
        "_value": 4
      },
      "ry": {
        "_dirName": "ry",
        "_dirType": "int",
        "_value": 0
      },
      "type": {
        "_dirName": "type",
        "_dirType": "int",
        "_value": 4
      },
      "cx": {
        "_dirName": "cx",
        "_dirType": "int",
        "_value": 800
      },
      "cy": {
        "_dirName": "cy",
        "_dirType": "int",
        "_value": 0
      },
      "a": {
        "_dirName": "a",
        "_dirType": "int",
        "_value": 255
      }
    },
    "5": {
      "_dirName": "5",
      "_dirType": "sub",
      "bS": {
        "_dirName": "bS",
        "_dirType": "string",
        "_value": "toyCastle"
      },
      "front": {
        "_dirName": "front",
        "_dirType": "int",
        "_value": 0
      },
      "ani": {
        "_dirName": "ani",
        "_dirType": "int",
        "_value": 0
      },
      "no": {
        "_dirName": "no",
        "_dirType": "int",
        "_value": 13
      },
      "f": {
        "_dirName": "f",
        "_dirType": "int",
        "_value": 0
      },
      "x": {
        "_dirName": "x",
        "_dirType": "int",
        "_value": 185
      },
      "y": {
        "_dirName": "y",
        "_dirType": "int",
        "_value": -614
      },
      "rx": {
        "_dirName": "rx",
        "_dirType": "int",
        "_value": 0
      },
      "ry": {
        "_dirName": "ry",
        "_dirType": "int",
        "_value": -50
      },
      "type": {
        "_dirName": "type",
        "_dirType": "int",
        "_value": 0
      },
      "cx": {
        "_dirName": "cx",
        "_dirType": "int",
        "_value": 0
      },
      "cy": {
        "_dirName": "cy",
        "_dirType": "int",
        "_value": 0
      },
      "a": {
        "_dirName": "a",
        "_dirType": "int",
        "_value": 255
      }
    }
  },
  "life": {
    "_dirName": "life",
    "_dirType": "sub"
  },
  "reactor": {
    "_dirName": "reactor",
    "_dirType": "sub"
  },
  "0": {
    "_dirName": "0",
    "_dirType": "sub",
    "info": {
      "_dirName": "info",
      "_dirType": "sub",
      "tS": {
        "_dirName": "tS",
        "_dirType": "string",
        "_value": "blankTower"
      },
      "tSMag": {
        "_dirName": "tSMag",
        "_dirType": "int",
        "_value": 1
      }
    },
    "tile": {
      "_dirName": "tile",
      "_dirType": "sub"
    },
    "obj": {
      "_dirName": "obj",
      "_dirType": "sub",
      "0": {
        "_dirName": "0",
        "_dirType": "sub",
        "oS": {
          "_dirName": "oS",
          "_dirType": "string",
          "_value": "houseTC"
        },
        "l0": {
          "_dirName": "l0",
          "_dirType": "string",
          "_value": "house8"
        },
        "l1": {
          "_dirName": "l1",
          "_dirType": "string",
          "_value": "basic"
        },
        "l2": {
          "_dirName": "l2",
          "_dirType": "string",
          "_value": "5"
        },
        "x": {
          "_dirName": "x",
          "_dirType": "int",
          "_value": -112
        },
        "y": {
          "_dirName": "y",
          "_dirType": "int",
          "_value": -690
        },
        "z": {
          "_dirName": "z",
          "_dirType": "int",
          "_value": 1
        },
        "f": {
          "_dirName": "f",
          "_dirType": "int",
          "_value": 1
        },
        "zM": {
          "_dirName": "zM",
          "_dirType": "int",
          "_value": 15
        }
      }
    }
  },
  "1": {
    "_dirName": "1",
    "_dirType": "sub",
    "info": {
      "_dirName": "info",
      "_dirType": "sub",
      "tS": {
        "_dirName": "tS",
        "_dirType": "string",
        "_value": "blankTower"
      },
      "tSMag": {
        "_dirName": "tSMag",
        "_dirType": "int",
        "_value": 1
      }
    },
    "tile": {
      "_dirName": "tile",
      "_dirType": "sub"
    },
    "obj": {
      "_dirName": "obj",
      "_dirType": "sub",
      "0": {
        "_dirName": "0",
        "_dirType": "sub",
        "oS": {
          "_dirName": "oS",
          "_dirType": "string",
          "_value": "insideTC"
        },
        "l0": {
          "_dirName": "l0",
          "_dirType": "string",
          "_value": "inside0"
        },
        "l1": {
          "_dirName": "l1",
          "_dirType": "string",
          "_value": "frame0"
        },
        "l2": {
          "_dirName": "l2",
          "_dirType": "string",
          "_value": "2"
        },
        "x": {
          "_dirName": "x",
          "_dirType": "int",
          "_value": 158
        },
        "y": {
          "_dirName": "y",
          "_dirType": "int",
          "_value": -882
        },
        "z": {
          "_dirName": "z",
          "_dirType": "int",
          "_value": 4
        },
        "f": {
          "_dirName": "f",
          "_dirType": "int",
          "_value": 1
        },
        "zM": {
          "_dirName": "zM",
          "_dirType": "int",
          "_value": 13
        }
      },
      "2": {
        "_dirName": "2",
        "_dirType": "sub",
        "oS": {
          "_dirName": "oS",
          "_dirType": "string",
          "_value": "insideTC"
        },
        "l0": {
          "_dirName": "l0",
          "_dirType": "string",
          "_value": "inside0"
        },
        "l1": {
          "_dirName": "l1",
          "_dirType": "string",
          "_value": "frame0"
        },
        "l2": {
          "_dirName": "l2",
          "_dirType": "string",
          "_value": "2"
        },
        "x": {
          "_dirName": "x",
          "_dirType": "int",
          "_value": 158
        },
        "y": {
          "_dirName": "y",
          "_dirType": "int",
          "_value": -156
        },
        "z": {
          "_dirName": "z",
          "_dirType": "int",
          "_value": 3
        },
        "f": {
          "_dirName": "f",
          "_dirType": "int",
          "_value": 1
        },
        "zM": {
          "_dirName": "zM",
          "_dirType": "int",
          "_value": 4
        }
      },
      "3": {
        "_dirName": "3",
        "_dirType": "sub",
        "oS": {
          "_dirName": "oS",
          "_dirType": "string",
          "_value": "insideTC"
        },
        "l0": {
          "_dirName": "l0",
          "_dirType": "string",
          "_value": "inside0"
        },
        "l1": {
          "_dirName": "l1",
          "_dirType": "string",
          "_value": "stairs"
        },
        "l2": {
          "_dirName": "l2",
          "_dirType": "string",
          "_value": "0"
        },
        "x": {
          "_dirName": "x",
          "_dirType": "int",
          "_value": 272
        },
        "y": {
          "_dirName": "y",
          "_dirType": "int",
          "_value": 149
        },
        "z": {
          "_dirName": "z",
          "_dirType": "int",
          "_value": 3
        },
        "f": {
          "_dirName": "f",
          "_dirType": "int",
          "_value": 0
        },
        "zM": {
          "_dirName": "zM",
          "_dirType": "int",
          "_value": 4
        }
      },
      "4": {
        "_dirName": "4",
        "_dirType": "sub",
        "oS": {
          "_dirName": "oS",
          "_dirType": "string",
          "_value": "insideTC"
        },
        "l0": {
          "_dirName": "l0",
          "_dirType": "string",
          "_value": "inside0"
        },
        "l1": {
          "_dirName": "l1",
          "_dirType": "string",
          "_value": "door"
        },
        "l2": {
          "_dirName": "l2",
          "_dirType": "string",
          "_value": "0"
        },
        "x": {
          "_dirName": "x",
          "_dirType": "int",
          "_value": 289
        },
        "y": {
          "_dirName": "y",
          "_dirType": "int",
          "_value": 26
        },
        "z": {
          "_dirName": "z",
          "_dirType": "int",
          "_value": 3
        },
        "f": {
          "_dirName": "f",
          "_dirType": "int",
          "_value": 0
        },
        "zM": {
          "_dirName": "zM",
          "_dirType": "int",
          "_value": 4
        }
      },
      "5": {
        "_dirName": "5",
        "_dirType": "sub",
        "oS": {
          "_dirName": "oS",
          "_dirType": "string",
          "_value": "insideTC"
        },
        "l0": {
          "_dirName": "l0",
          "_dirType": "string",
          "_value": "inside0"
        },
        "l1": {
          "_dirName": "l1",
          "_dirType": "string",
          "_value": "box"
        },
        "l2": {
          "_dirName": "l2",
          "_dirType": "string",
          "_value": "0"
        },
        "x": {
          "_dirName": "x",
          "_dirType": "int",
          "_value": -357
        },
        "y": {
          "_dirName": "y",
          "_dirType": "int",
          "_value": 140
        },
        "z": {
          "_dirName": "z",
          "_dirType": "int",
          "_value": 5
        },
        "f": {
          "_dirName": "f",
          "_dirType": "int",
          "_value": 0
        },
        "zM": {
          "_dirName": "zM",
          "_dirType": "int",
          "_value": 5
        }
      },
      "1": {
        "_dirName": "1",
        "_dirType": "sub",
        "oS": {
          "_dirName": "oS",
          "_dirType": "string",
          "_value": "insideTC"
        },
        "l0": {
          "_dirName": "l0",
          "_dirType": "string",
          "_value": "inside0"
        },
        "l1": {
          "_dirName": "l1",
          "_dirType": "string",
          "_value": "box"
        },
        "l2": {
          "_dirName": "l2",
          "_dirType": "string",
          "_value": "1"
        },
        "x": {
          "_dirName": "x",
          "_dirType": "int",
          "_value": -282
        },
        "y": {
          "_dirName": "y",
          "_dirType": "int",
          "_value": 140
        },
        "z": {
          "_dirName": "z",
          "_dirType": "int",
          "_value": 4
        },
        "f": {
          "_dirName": "f",
          "_dirType": "int",
          "_value": 0
        },
        "zM": {
          "_dirName": "zM",
          "_dirType": "int",
          "_value": 5
        }
      },
      "7": {
        "_dirName": "7",
        "_dirType": "sub",
        "oS": {
          "_dirName": "oS",
          "_dirType": "string",
          "_value": "insideTC"
        },
        "l0": {
          "_dirName": "l0",
          "_dirType": "string",
          "_value": "inside0"
        },
        "l1": {
          "_dirName": "l1",
          "_dirType": "string",
          "_value": "box"
        },
        "l2": {
          "_dirName": "l2",
          "_dirType": "string",
          "_value": "5"
        },
        "x": {
          "_dirName": "x",
          "_dirType": "int",
          "_value": -326
        },
        "y": {
          "_dirName": "y",
          "_dirType": "int",
          "_value": 142
        },
        "z": {
          "_dirName": "z",
          "_dirType": "int",
          "_value": 5
        },
        "f": {
          "_dirName": "f",
          "_dirType": "int",
          "_value": 0
        },
        "zM": {
          "_dirName": "zM",
          "_dirType": "int",
          "_value": 5
        }
      },
      "8": {
        "_dirName": "8",
        "_dirType": "sub",
        "oS": {
          "_dirName": "oS",
          "_dirType": "string",
          "_value": "insideTC"
        },
        "l0": {
          "_dirName": "l0",
          "_dirType": "string",
          "_value": "inside0"
        },
        "l1": {
          "_dirName": "l1",
          "_dirType": "string",
          "_value": "box"
        },
        "l2": {
          "_dirName": "l2",
          "_dirType": "string",
          "_value": "7"
        },
        "x": {
          "_dirName": "x",
          "_dirType": "int",
          "_value": -251
        },
        "y": {
          "_dirName": "y",
          "_dirType": "int",
          "_value": 142
        },
        "z": {
          "_dirName": "z",
          "_dirType": "int",
          "_value": 5
        },
        "f": {
          "_dirName": "f",
          "_dirType": "int",
          "_value": 0
        },
        "zM": {
          "_dirName": "zM",
          "_dirType": "int",
          "_value": 5
        }
      },
      "10": {
        "_dirName": "10",
        "_dirType": "sub",
        "oS": {
          "_dirName": "oS",
          "_dirType": "string",
          "_value": "insideTC"
        },
        "l0": {
          "_dirName": "l0",
          "_dirType": "string",
          "_value": "inside0"
        },
        "l1": {
          "_dirName": "l1",
          "_dirType": "string",
          "_value": "curtain"
        },
        "l2": {
          "_dirName": "l2",
          "_dirType": "string",
          "_value": "2"
        },
        "x": {
          "_dirName": "x",
          "_dirType": "int",
          "_value": -83
        },
        "y": {
          "_dirName": "y",
          "_dirType": "int",
          "_value": -1095
        },
        "z": {
          "_dirName": "z",
          "_dirType": "int",
          "_value": 4
        },
        "f": {
          "_dirName": "f",
          "_dirType": "int",
          "_value": 1
        },
        "zM": {
          "_dirName": "zM",
          "_dirType": "int",
          "_value": 13
        }
      },
      "11": {
        "_dirName": "11",
        "_dirType": "sub",
        "oS": {
          "_dirName": "oS",
          "_dirType": "string",
          "_value": "insideTC"
        },
        "l0": {
          "_dirName": "l0",
          "_dirType": "string",
          "_value": "inside0"
        },
        "l1": {
          "_dirName": "l1",
          "_dirType": "string",
          "_value": "curtain"
        },
        "l2": {
          "_dirName": "l2",
          "_dirType": "string",
          "_value": "0"
        },
        "x": {
          "_dirName": "x",
          "_dirType": "int",
          "_value": -86
        },
        "y": {
          "_dirName": "y",
          "_dirType": "int",
          "_value": -325
        },
        "z": {
          "_dirName": "z",
          "_dirType": "int",
          "_value": 4
        },
        "f": {
          "_dirName": "f",
          "_dirType": "int",
          "_value": 1
        },
        "zM": {
          "_dirName": "zM",
          "_dirType": "int",
          "_value": 5
        }
      },
      "12": {
        "_dirName": "12",
        "_dirType": "sub",
        "oS": {
          "_dirName": "oS",
          "_dirType": "string",
          "_value": "insideTC"
        },
        "l0": {
          "_dirName": "l0",
          "_dirType": "string",
          "_value": "inside0"
        },
        "l1": {
          "_dirName": "l1",
          "_dirType": "string",
          "_value": "acc"
        },
        "l2": {
          "_dirName": "l2",
          "_dirType": "string",
          "_value": "2"
        },
        "x": {
          "_dirName": "x",
          "_dirType": "int",
          "_value": -333
        },
        "y": {
          "_dirName": "y",
          "_dirType": "int",
          "_value": 59
        },
        "z": {
          "_dirName": "z",
          "_dirType": "int",
          "_value": 3
        },
        "f": {
          "_dirName": "f",
          "_dirType": "int",
          "_value": 0
        },
        "zM": {
          "_dirName": "zM",
          "_dirType": "int",
          "_value": 5
        }
      },
      "13": {
        "_dirName": "13",
        "_dirType": "sub",
        "oS": {
          "_dirName": "oS",
          "_dirType": "string",
          "_value": "insideTC"
        },
        "l0": {
          "_dirName": "l0",
          "_dirType": "string",
          "_value": "inside0"
        },
        "l1": {
          "_dirName": "l1",
          "_dirType": "string",
          "_value": "box"
        },
        "l2": {
          "_dirName": "l2",
          "_dirType": "string",
          "_value": "3"
        },
        "x": {
          "_dirName": "x",
          "_dirType": "int",
          "_value": -359
        },
        "y": {
          "_dirName": "y",
          "_dirType": "int",
          "_value": -26
        },
        "z": {
          "_dirName": "z",
          "_dirType": "int",
          "_value": 3
        },
        "f": {
          "_dirName": "f",
          "_dirType": "int",
          "_value": 0
        },
        "zM": {
          "_dirName": "zM",
          "_dirType": "int",
          "_value": 5
        }
      },
      "14": {
        "_dirName": "14",
        "_dirType": "sub",
        "oS": {
          "_dirName": "oS",
          "_dirType": "string",
          "_value": "insideTC"
        },
        "l0": {
          "_dirName": "l0",
          "_dirType": "string",
          "_value": "inside0"
        },
        "l1": {
          "_dirName": "l1",
          "_dirType": "string",
          "_value": "box"
        },
        "l2": {
          "_dirName": "l2",
          "_dirType": "string",
          "_value": "1"
        },
        "x": {
          "_dirName": "x",
          "_dirType": "int",
          "_value": -310
        },
        "y": {
          "_dirName": "y",
          "_dirType": "int",
          "_value": -102
        },
        "z": {
          "_dirName": "z",
          "_dirType": "int",
          "_value": 3
        },
        "f": {
          "_dirName": "f",
          "_dirType": "int",
          "_value": 0
        },
        "zM": {
          "_dirName": "zM",
          "_dirType": "int",
          "_value": 5
        }
      },
      "16": {
        "_dirName": "16",
        "_dirType": "sub",
        "oS": {
          "_dirName": "oS",
          "_dirType": "string",
          "_value": "insideTC"
        },
        "l0": {
          "_dirName": "l0",
          "_dirType": "string",
          "_value": "inside0"
        },
        "l1": {
          "_dirName": "l1",
          "_dirType": "string",
          "_value": "box"
        },
        "l2": {
          "_dirName": "l2",
          "_dirType": "string",
          "_value": "4"
        },
        "x": {
          "_dirName": "x",
          "_dirType": "int",
          "_value": -283
        },
        "y": {
          "_dirName": "y",
          "_dirType": "int",
          "_value": -26
        },
        "z": {
          "_dirName": "z",
          "_dirType": "int",
          "_value": 2
        },
        "f": {
          "_dirName": "f",
          "_dirType": "int",
          "_value": 0
        },
        "zM": {
          "_dirName": "zM",
          "_dirType": "int",
          "_value": 5
        }
      },
      "17": {
        "_dirName": "17",
        "_dirType": "sub",
        "oS": {
          "_dirName": "oS",
          "_dirType": "string",
          "_value": "insideTC"
        },
        "l0": {
          "_dirName": "l0",
          "_dirType": "string",
          "_value": "inside0"
        },
        "l1": {
          "_dirName": "l1",
          "_dirType": "string",
          "_value": "wall0"
        },
        "l2": {
          "_dirName": "l2",
          "_dirType": "string",
          "_value": "0"
        },
        "x": {
          "_dirName": "x",
          "_dirType": "int",
          "_value": -108
        },
        "y": {
          "_dirName": "y",
          "_dirType": "int",
          "_value": -926
        },
        "z": {
          "_dirName": "z",
          "_dirType": "int",
          "_value": 2
        },
        "f": {
          "_dirName": "f",
          "_dirType": "int",
          "_value": 1
        },
        "zM": {
          "_dirName": "zM",
          "_dirType": "int",
          "_value": 13
        }
      },
      "18": {
        "_dirName": "18",
        "_dirType": "sub",
        "oS": {
          "_dirName": "oS",
          "_dirType": "string",
          "_value": "insideTC"
        },
        "l0": {
          "_dirName": "l0",
          "_dirType": "string",
          "_value": "inside0"
        },
        "l1": {
          "_dirName": "l1",
          "_dirType": "string",
          "_value": "wall1"
        },
        "l2": {
          "_dirName": "l2",
          "_dirType": "string",
          "_value": "4"
        },
        "x": {
          "_dirName": "x",
          "_dirType": "int",
          "_value": 278
        },
        "y": {
          "_dirName": "y",
          "_dirType": "int",
          "_value": -926
        },
        "z": {
          "_dirName": "z",
          "_dirType": "int",
          "_value": 2
        },
        "f": {
          "_dirName": "f",
          "_dirType": "int",
          "_value": 0
        },
        "zM": {
          "_dirName": "zM",
          "_dirType": "int",
          "_value": 13
        }
      },
      "6": {
        "_dirName": "6",
        "_dirType": "sub",
        "oS": {
          "_dirName": "oS",
          "_dirType": "string",
          "_value": "insideTC"
        },
        "l0": {
          "_dirName": "l0",
          "_dirType": "string",
          "_value": "inside0"
        },
        "l1": {
          "_dirName": "l1",
          "_dirType": "string",
          "_value": "wall1"
        },
        "l2": {
          "_dirName": "l2",
          "_dirType": "string",
          "_value": "4"
        },
        "x": {
          "_dirName": "x",
          "_dirType": "int",
          "_value": 322
        },
        "y": {
          "_dirName": "y",
          "_dirType": "int",
          "_value": -160
        },
        "z": {
          "_dirName": "z",
          "_dirType": "int",
          "_value": 1
        },
        "f": {
          "_dirName": "f",
          "_dirType": "int",
          "_value": 1
        },
        "zM": {
          "_dirName": "zM",
          "_dirType": "int",
          "_value": 4
        }
      },
      "9": {
        "_dirName": "9",
        "_dirType": "sub",
        "oS": {
          "_dirName": "oS",
          "_dirType": "string",
          "_value": "insideTC"
        },
        "l0": {
          "_dirName": "l0",
          "_dirType": "string",
          "_value": "inside0"
        },
        "l1": {
          "_dirName": "l1",
          "_dirType": "string",
          "_value": "wall0"
        },
        "l2": {
          "_dirName": "l2",
          "_dirType": "string",
          "_value": "2"
        },
        "x": {
          "_dirName": "x",
          "_dirType": "int",
          "_value": -209
        },
        "y": {
          "_dirName": "y",
          "_dirType": "int",
          "_value": -162
        },
        "z": {
          "_dirName": "z",
          "_dirType": "int",
          "_value": 1
        },
        "f": {
          "_dirName": "f",
          "_dirType": "int",
          "_value": 0
        },
        "zM": {
          "_dirName": "zM",
          "_dirType": "int",
          "_value": 5
        }
      },
      "19": {
        "_dirName": "19",
        "_dirType": "sub",
        "oS": {
          "_dirName": "oS",
          "_dirType": "string",
          "_value": "insideTC"
        },
        "l0": {
          "_dirName": "l0",
          "_dirType": "string",
          "_value": "inside0"
        },
        "l1": {
          "_dirName": "l1",
          "_dirType": "string",
          "_value": "acc"
        },
        "l2": {
          "_dirName": "l2",
          "_dirType": "string",
          "_value": "13"
        },
        "x": {
          "_dirName": "x",
          "_dirType": "int",
          "_value": 51
        },
        "y": {
          "_dirName": "y",
          "_dirType": "int",
          "_value": -28
        },
        "z": {
          "_dirName": "z",
          "_dirType": "int",
          "_value": 3
        },
        "f": {
          "_dirName": "f",
          "_dirType": "int",
          "_value": 1
        },
        "zM": {
          "_dirName": "zM",
          "_dirType": "int",
          "_value": 5
        }
      },
      "20": {
        "_dirName": "20",
        "_dirType": "sub",
        "oS": {
          "_dirName": "oS",
          "_dirType": "string",
          "_value": "insideTC"
        },
        "l0": {
          "_dirName": "l0",
          "_dirType": "string",
          "_value": "inside0"
        },
        "l1": {
          "_dirName": "l1",
          "_dirType": "string",
          "_value": "acc"
        },
        "l2": {
          "_dirName": "l2",
          "_dirType": "string",
          "_value": "14"
        },
        "x": {
          "_dirName": "x",
          "_dirType": "int",
          "_value": -18
        },
        "y": {
          "_dirName": "y",
          "_dirType": "int",
          "_value": -28
        },
        "z": {
          "_dirName": "z",
          "_dirType": "int",
          "_value": 3
        },
        "f": {
          "_dirName": "f",
          "_dirType": "int",
          "_value": 1
        },
        "zM": {
          "_dirName": "zM",
          "_dirType": "int",
          "_value": 5
        }
      },
      "21": {
        "_dirName": "21",
        "_dirType": "sub",
        "oS": {
          "_dirName": "oS",
          "_dirType": "string",
          "_value": "insideTC"
        },
        "l0": {
          "_dirName": "l0",
          "_dirType": "string",
          "_value": "inside0"
        },
        "l1": {
          "_dirName": "l1",
          "_dirType": "string",
          "_value": "acc"
        },
        "l2": {
          "_dirName": "l2",
          "_dirType": "string",
          "_value": "1"
        },
        "x": {
          "_dirName": "x",
          "_dirType": "int",
          "_value": -23
        },
        "y": {
          "_dirName": "y",
          "_dirType": "int",
          "_value": -124
        },
        "z": {
          "_dirName": "z",
          "_dirType": "int",
          "_value": 3
        },
        "f": {
          "_dirName": "f",
          "_dirType": "int",
          "_value": 1
        },
        "zM": {
          "_dirName": "zM",
          "_dirType": "int",
          "_value": 5
        }
      },
      "23": {
        "_dirName": "23",
        "_dirType": "sub",
        "oS": {
          "_dirName": "oS",
          "_dirType": "string",
          "_value": "insideTC"
        },
        "l0": {
          "_dirName": "l0",
          "_dirType": "string",
          "_value": "inside0"
        },
        "l1": {
          "_dirName": "l1",
          "_dirType": "string",
          "_value": "acc"
        },
        "l2": {
          "_dirName": "l2",
          "_dirType": "string",
          "_value": "18"
        },
        "x": {
          "_dirName": "x",
          "_dirType": "int",
          "_value": 20
        },
        "y": {
          "_dirName": "y",
          "_dirType": "int",
          "_value": -195
        },
        "z": {
          "_dirName": "z",
          "_dirType": "int",
          "_value": 3
        },
        "f": {
          "_dirName": "f",
          "_dirType": "int",
          "_value": 0
        },
        "zM": {
          "_dirName": "zM",
          "_dirType": "int",
          "_value": 5
        }
      },
      "24": {
        "_dirName": "24",
        "_dirType": "sub",
        "oS": {
          "_dirName": "oS",
          "_dirType": "string",
          "_value": "insideTC"
        },
        "l0": {
          "_dirName": "l0",
          "_dirType": "string",
          "_value": "inside0"
        },
        "l1": {
          "_dirName": "l1",
          "_dirType": "string",
          "_value": "acc"
        },
        "l2": {
          "_dirName": "l2",
          "_dirType": "string",
          "_value": "16"
        },
        "x": {
          "_dirName": "x",
          "_dirType": "int",
          "_value": -56
        },
        "y": {
          "_dirName": "y",
          "_dirType": "int",
          "_value": -194
        },
        "z": {
          "_dirName": "z",
          "_dirType": "int",
          "_value": 3
        },
        "f": {
          "_dirName": "f",
          "_dirType": "int",
          "_value": 0
        },
        "zM": {
          "_dirName": "zM",
          "_dirType": "int",
          "_value": 5
        }
      },
      "25": {
        "_dirName": "25",
        "_dirType": "sub",
        "oS": {
          "_dirName": "oS",
          "_dirType": "string",
          "_value": "insideTC"
        },
        "l0": {
          "_dirName": "l0",
          "_dirType": "string",
          "_value": "inside0"
        },
        "l1": {
          "_dirName": "l1",
          "_dirType": "string",
          "_value": "box"
        },
        "l2": {
          "_dirName": "l2",
          "_dirType": "string",
          "_value": "13"
        },
        "x": {
          "_dirName": "x",
          "_dirType": "int",
          "_value": -330
        },
        "y": {
          "_dirName": "y",
          "_dirType": "int",
          "_value": -17
        },
        "z": {
          "_dirName": "z",
          "_dirType": "int",
          "_value": 3
        },
        "f": {
          "_dirName": "f",
          "_dirType": "int",
          "_value": 0
        },
        "zM": {
          "_dirName": "zM",
          "_dirType": "int",
          "_value": 5
        }
      },
      "15": {
        "_dirName": "15",
        "_dirType": "sub",
        "oS": {
          "_dirName": "oS",
          "_dirType": "string",
          "_value": "insideTC"
        },
        "l0": {
          "_dirName": "l0",
          "_dirType": "string",
          "_value": "inside0"
        },
        "l1": {
          "_dirName": "l1",
          "_dirType": "string",
          "_value": "box"
        },
        "l2": {
          "_dirName": "l2",
          "_dirType": "string",
          "_value": "10"
        },
        "x": {
          "_dirName": "x",
          "_dirType": "int",
          "_value": -290
        },
        "y": {
          "_dirName": "y",
          "_dirType": "int",
          "_value": -86
        },
        "z": {
          "_dirName": "z",
          "_dirType": "int",
          "_value": 3
        },
        "f": {
          "_dirName": "f",
          "_dirType": "int",
          "_value": 0
        },
        "zM": {
          "_dirName": "zM",
          "_dirType": "int",
          "_value": 5
        }
      },
      "22": {
        "_dirName": "22",
        "_dirType": "sub",
        "oS": {
          "_dirName": "oS",
          "_dirType": "string",
          "_value": "insideTC"
        },
        "l0": {
          "_dirName": "l0",
          "_dirType": "string",
          "_value": "inside0"
        },
        "l1": {
          "_dirName": "l1",
          "_dirType": "string",
          "_value": "box"
        },
        "l2": {
          "_dirName": "l2",
          "_dirType": "string",
          "_value": "12"
        },
        "x": {
          "_dirName": "x",
          "_dirType": "int",
          "_value": -253
        },
        "y": {
          "_dirName": "y",
          "_dirType": "int",
          "_value": -23
        },
        "z": {
          "_dirName": "z",
          "_dirType": "int",
          "_value": 3
        },
        "f": {
          "_dirName": "f",
          "_dirType": "int",
          "_value": 0
        },
        "zM": {
          "_dirName": "zM",
          "_dirType": "int",
          "_value": 5
        }
      }
    }
  },
  "2": {
    "_dirName": "2",
    "_dirType": "sub",
    "info": {
      "_dirName": "info",
      "_dirType": "sub",
      "tS": {
        "_dirName": "tS",
        "_dirType": "string",
        "_value": "blankTower"
      },
      "tSMag": {
        "_dirName": "tSMag",
        "_dirType": "int",
        "_value": 1
      }
    },
    "tile": {
      "_dirName": "tile",
      "_dirType": "sub"
    },
    "obj": {
      "_dirName": "obj",
      "_dirType": "sub",
      "0": {
        "_dirName": "0",
        "_dirType": "sub",
        "oS": {
          "_dirName": "oS",
          "_dirType": "string",
          "_value": "insideTC"
        },
        "l0": {
          "_dirName": "l0",
          "_dirType": "string",
          "_value": "inside0"
        },
        "l1": {
          "_dirName": "l1",
          "_dirType": "string",
          "_value": "acc"
        },
        "l2": {
          "_dirName": "l2",
          "_dirType": "string",
          "_value": "19"
        },
        "x": {
          "_dirName": "x",
          "_dirType": "int",
          "_value": -32
        },
        "y": {
          "_dirName": "y",
          "_dirType": "int",
          "_value": 103
        },
        "z": {
          "_dirName": "z",
          "_dirType": "int",
          "_value": 3
        },
        "f": {
          "_dirName": "f",
          "_dirType": "int",
          "_value": 0
        },
        "zM": {
          "_dirName": "zM",
          "_dirType": "int",
          "_value": 6
        }
      },
      "1": {
        "_dirName": "1",
        "_dirType": "sub",
        "oS": {
          "_dirName": "oS",
          "_dirType": "string",
          "_value": "insideTC"
        },
        "l0": {
          "_dirName": "l0",
          "_dirType": "string",
          "_value": "inside0"
        },
        "l1": {
          "_dirName": "l1",
          "_dirType": "string",
          "_value": "acc"
        },
        "l2": {
          "_dirName": "l2",
          "_dirType": "string",
          "_value": "5"
        },
        "x": {
          "_dirName": "x",
          "_dirType": "int",
          "_value": 196
        },
        "y": {
          "_dirName": "y",
          "_dirType": "int",
          "_value": -214
        },
        "z": {
          "_dirName": "z",
          "_dirType": "int",
          "_value": 3
        },
        "f": {
          "_dirName": "f",
          "_dirType": "int",
          "_value": 1
        },
        "zM": {
          "_dirName": "zM",
          "_dirType": "int",
          "_value": 7
        }
      },
      "2": {
        "_dirName": "2",
        "_dirType": "sub",
        "oS": {
          "_dirName": "oS",
          "_dirType": "string",
          "_value": "insideTC"
        },
        "l0": {
          "_dirName": "l0",
          "_dirType": "string",
          "_value": "inside0"
        },
        "l1": {
          "_dirName": "l1",
          "_dirType": "string",
          "_value": "acc"
        },
        "l2": {
          "_dirName": "l2",
          "_dirType": "string",
          "_value": "12"
        },
        "x": {
          "_dirName": "x",
          "_dirType": "int",
          "_value": 283
        },
        "y": {
          "_dirName": "y",
          "_dirType": "int",
          "_value": -181
        },
        "z": {
          "_dirName": "z",
          "_dirType": "int",
          "_value": 3
        },
        "f": {
          "_dirName": "f",
          "_dirType": "int",
          "_value": 0
        },
        "zM": {
          "_dirName": "zM",
          "_dirType": "int",
          "_value": 7
        }
      }
    }
  },
  "3": {
    "_dirName": "3",
    "_dirType": "sub",
    "info": {
      "_dirName": "info",
      "_dirType": "sub",
      "tS": {
        "_dirName": "tS",
        "_dirType": "string",
        "_value": "blankTower"
      },
      "tSMag": {
        "_dirName": "tSMag",
        "_dirType": "int",
        "_value": 1
      }
    },
    "tile": {
      "_dirName": "tile",
      "_dirType": "sub"
    },
    "obj": {
      "_dirName": "obj",
      "_dirType": "sub",
      "0": {
        "_dirName": "0",
        "_dirType": "sub",
        "oS": {
          "_dirName": "oS",
          "_dirType": "string",
          "_value": "insideTC"
        },
        "l0": {
          "_dirName": "l0",
          "_dirType": "string",
          "_value": "inside0"
        },
        "l1": {
          "_dirName": "l1",
          "_dirType": "string",
          "_value": "frame0"
        },
        "l2": {
          "_dirName": "l2",
          "_dirType": "string",
          "_value": "0"
        },
        "x": {
          "_dirName": "x",
          "_dirType": "int",
          "_value": -111
        },
        "y": {
          "_dirName": "y",
          "_dirType": "int",
          "_value": 263
        },
        "z": {
          "_dirName": "z",
          "_dirType": "int",
          "_value": 3
        },
        "f": {
          "_dirName": "f",
          "_dirType": "int",
          "_value": 0
        },
        "zM": {
          "_dirName": "zM",
          "_dirType": "int",
          "_value": 0
        }
      },
      "1": {
        "_dirName": "1",
        "_dirType": "sub",
        "oS": {
          "_dirName": "oS",
          "_dirType": "string",
          "_value": "insideTC"
        },
        "l0": {
          "_dirName": "l0",
          "_dirType": "string",
          "_value": "inside0"
        },
        "l1": {
          "_dirName": "l1",
          "_dirType": "string",
          "_value": "acc"
        },
        "l2": {
          "_dirName": "l2",
          "_dirType": "string",
          "_value": "7"
        },
        "x": {
          "_dirName": "x",
          "_dirType": "int",
          "_value": 95
        },
        "y": {
          "_dirName": "y",
          "_dirType": "int",
          "_value": -889
        },
        "z": {
          "_dirName": "z",
          "_dirType": "int",
          "_value": 3
        },
        "f": {
          "_dirName": "f",
          "_dirType": "int",
          "_value": 1
        },
        "zM": {
          "_dirName": "zM",
          "_dirType": "int",
          "_value": 20
        }
      },
      "2": {
        "_dirName": "2",
        "_dirType": "sub",
        "oS": {
          "_dirName": "oS",
          "_dirType": "string",
          "_value": "insideTC"
        },
        "l0": {
          "_dirName": "l0",
          "_dirType": "string",
          "_value": "inside0"
        },
        "l1": {
          "_dirName": "l1",
          "_dirType": "string",
          "_value": "acc"
        },
        "l2": {
          "_dirName": "l2",
          "_dirType": "string",
          "_value": "4"
        },
        "x": {
          "_dirName": "x",
          "_dirType": "int",
          "_value": 199
        },
        "y": {
          "_dirName": "y",
          "_dirType": "int",
          "_value": -818
        },
        "z": {
          "_dirName": "z",
          "_dirType": "int",
          "_value": 3
        },
        "f": {
          "_dirName": "f",
          "_dirType": "int",
          "_value": 1
        },
        "zM": {
          "_dirName": "zM",
          "_dirType": "int",
          "_value": 18
        }
      },
      "3": {
        "_dirName": "3",
        "_dirType": "sub",
        "oS": {
          "_dirName": "oS",
          "_dirType": "string",
          "_value": "insideTC"
        },
        "l0": {
          "_dirName": "l0",
          "_dirType": "string",
          "_value": "inside0"
        },
        "l1": {
          "_dirName": "l1",
          "_dirType": "string",
          "_value": "acc"
        },
        "l2": {
          "_dirName": "l2",
          "_dirType": "string",
          "_value": "2"
        },
        "x": {
          "_dirName": "x",
          "_dirType": "int",
          "_value": 319
        },
        "y": {
          "_dirName": "y",
          "_dirType": "int",
          "_value": -937
        },
        "z": {
          "_dirName": "z",
          "_dirType": "int",
          "_value": 3
        },
        "f": {
          "_dirName": "f",
          "_dirType": "int",
          "_value": 1
        },
        "zM": {
          "_dirName": "zM",
          "_dirType": "int",
          "_value": 22
        }
      },
      "4": {
        "_dirName": "4",
        "_dirType": "sub",
        "oS": {
          "_dirName": "oS",
          "_dirType": "string",
          "_value": "insideTC"
        },
        "l0": {
          "_dirName": "l0",
          "_dirType": "string",
          "_value": "inside0"
        },
        "l1": {
          "_dirName": "l1",
          "_dirType": "string",
          "_value": "acc"
        },
        "l2": {
          "_dirName": "l2",
          "_dirType": "string",
          "_value": "21"
        },
        "x": {
          "_dirName": "x",
          "_dirType": "int",
          "_value": 237
        },
        "y": {
          "_dirName": "y",
          "_dirType": "int",
          "_value": -666
        },
        "z": {
          "_dirName": "z",
          "_dirType": "int",
          "_value": 3
        },
        "f": {
          "_dirName": "f",
          "_dirType": "int",
          "_value": 1
        },
        "zM": {
          "_dirName": "zM",
          "_dirType": "int",
          "_value": 10
        }
      },
      "5": {
        "_dirName": "5",
        "_dirType": "sub",
        "oS": {
          "_dirName": "oS",
          "_dirType": "string",
          "_value": "insideTC"
        },
        "l0": {
          "_dirName": "l0",
          "_dirType": "string",
          "_value": "inside0"
        },
        "l1": {
          "_dirName": "l1",
          "_dirType": "string",
          "_value": "frame0"
        },
        "l2": {
          "_dirName": "l2",
          "_dirType": "string",
          "_value": "0"
        },
        "x": {
          "_dirName": "x",
          "_dirType": "int",
          "_value": -112
        },
        "y": {
          "_dirName": "y",
          "_dirType": "int",
          "_value": -504
        },
        "z": {
          "_dirName": "z",
          "_dirType": "int",
          "_value": 3
        },
        "f": {
          "_dirName": "f",
          "_dirType": "int",
          "_value": 0
        },
        "zM": {
          "_dirName": "zM",
          "_dirType": "int",
          "_value": 10
        }
      }
    }
  },
  "4": {
    "_dirName": "4",
    "_dirType": "sub",
    "info": {
      "_dirName": "info",
      "_dirType": "sub",
      "tS": {
        "_dirName": "tS",
        "_dirType": "string",
        "_value": "blankTower"
      },
      "tSMag": {
        "_dirName": "tSMag",
        "_dirType": "int",
        "_value": 1
      }
    },
    "tile": {
      "_dirName": "tile",
      "_dirType": "sub"
    },
    "obj": {
      "_dirName": "obj",
      "_dirType": "sub",
      "0": {
        "_dirName": "0",
        "_dirType": "sub",
        "oS": {
          "_dirName": "oS",
          "_dirType": "string",
          "_value": "insideTC"
        },
        "l0": {
          "_dirName": "l0",
          "_dirType": "string",
          "_value": "inside0"
        },
        "l1": {
          "_dirName": "l1",
          "_dirType": "string",
          "_value": "frame0"
        },
        "l2": {
          "_dirName": "l2",
          "_dirType": "string",
          "_value": "1"
        },
        "x": {
          "_dirName": "x",
          "_dirType": "int",
          "_value": 441
        },
        "y": {
          "_dirName": "y",
          "_dirType": "int",
          "_value": -88
        },
        "z": {
          "_dirName": "z",
          "_dirType": "int",
          "_value": 6
        },
        "f": {
          "_dirName": "f",
          "_dirType": "int",
          "_value": 0
        },
        "zM": {
          "_dirName": "zM",
          "_dirType": "int",
          "_value": 3
        }
      },
      "1": {
        "_dirName": "1",
        "_dirType": "sub",
        "oS": {
          "_dirName": "oS",
          "_dirType": "string",
          "_value": "insideTC"
        },
        "l0": {
          "_dirName": "l0",
          "_dirType": "string",
          "_value": "inside0"
        },
        "l1": {
          "_dirName": "l1",
          "_dirType": "string",
          "_value": "frame0"
        },
        "l2": {
          "_dirName": "l2",
          "_dirType": "string",
          "_value": "1"
        },
        "x": {
          "_dirName": "x",
          "_dirType": "int",
          "_value": -443
        },
        "y": {
          "_dirName": "y",
          "_dirType": "int",
          "_value": -85
        },
        "z": {
          "_dirName": "z",
          "_dirType": "int",
          "_value": 4
        },
        "f": {
          "_dirName": "f",
          "_dirType": "int",
          "_value": 1
        },
        "zM": {
          "_dirName": "zM",
          "_dirType": "int",
          "_value": 2
        }
      },
      "2": {
        "_dirName": "2",
        "_dirType": "sub",
        "oS": {
          "_dirName": "oS",
          "_dirType": "string",
          "_value": "insideTC"
        },
        "l0": {
          "_dirName": "l0",
          "_dirType": "string",
          "_value": "inside0"
        },
        "l1": {
          "_dirName": "l1",
          "_dirType": "string",
          "_value": "frame0"
        },
        "l2": {
          "_dirName": "l2",
          "_dirType": "string",
          "_value": "1"
        },
        "x": {
          "_dirName": "x",
          "_dirType": "int",
          "_value": 443
        },
        "y": {
          "_dirName": "y",
          "_dirType": "int",
          "_value": -851
        },
        "z": {
          "_dirName": "z",
          "_dirType": "int",
          "_value": 5
        },
        "f": {
          "_dirName": "f",
          "_dirType": "int",
          "_value": 0
        },
        "zM": {
          "_dirName": "zM",
          "_dirType": "int",
          "_value": 12
        }
      },
      "3": {
        "_dirName": "3",
        "_dirType": "sub",
        "oS": {
          "_dirName": "oS",
          "_dirType": "string",
          "_value": "insideTC"
        },
        "l0": {
          "_dirName": "l0",
          "_dirType": "string",
          "_value": "inside0"
        },
        "l1": {
          "_dirName": "l1",
          "_dirType": "string",
          "_value": "frame0"
        },
        "l2": {
          "_dirName": "l2",
          "_dirType": "string",
          "_value": "1"
        },
        "x": {
          "_dirName": "x",
          "_dirType": "int",
          "_value": -443
        },
        "y": {
          "_dirName": "y",
          "_dirType": "int",
          "_value": -852
        },
        "z": {
          "_dirName": "z",
          "_dirType": "int",
          "_value": 3
        },
        "f": {
          "_dirName": "f",
          "_dirType": "int",
          "_value": 1
        },
        "zM": {
          "_dirName": "zM",
          "_dirType": "int",
          "_value": 2
        }
      },
      "4": {
        "_dirName": "4",
        "_dirType": "sub",
        "oS": {
          "_dirName": "oS",
          "_dirType": "string",
          "_value": "connect"
        },
        "l0": {
          "_dirName": "l0",
          "_dirType": "string",
          "_value": "ladder"
        },
        "l1": {
          "_dirName": "l1",
          "_dirType": "string",
          "_value": "20"
        },
        "l2": {
          "_dirName": "l2",
          "_dirType": "string",
          "_value": "0"
        },
        "x": {
          "_dirName": "x",
          "_dirType": "int",
          "_value": -282
        },
        "y": {
          "_dirName": "y",
          "_dirType": "int",
          "_value": -583
        },
        "z": {
          "_dirName": "z",
          "_dirType": "int",
          "_value": 2
        },
        "f": {
          "_dirName": "f",
          "_dirType": "int",
          "_value": 1
        },
        "zM": {
          "_dirName": "zM",
          "_dirType": "int",
          "_value": 14
        }
      },
      "5": {
        "_dirName": "5",
        "_dirType": "sub",
        "oS": {
          "_dirName": "oS",
          "_dirType": "string",
          "_value": "connect"
        },
        "l0": {
          "_dirName": "l0",
          "_dirType": "string",
          "_value": "ladder"
        },
        "l1": {
          "_dirName": "l1",
          "_dirType": "string",
          "_value": "20"
        },
        "l2": {
          "_dirName": "l2",
          "_dirType": "string",
          "_value": "2"
        },
        "x": {
          "_dirName": "x",
          "_dirType": "int",
          "_value": -282
        },
        "y": {
          "_dirName": "y",
          "_dirType": "int",
          "_value": -533
        },
        "z": {
          "_dirName": "z",
          "_dirType": "int",
          "_value": 3
        },
        "f": {
          "_dirName": "f",
          "_dirType": "int",
          "_value": 1
        },
        "zM": {
          "_dirName": "zM",
          "_dirType": "int",
          "_value": 9
        }
      },
      "6": {
        "_dirName": "6",
        "_dirType": "sub",
        "oS": {
          "_dirName": "oS",
          "_dirType": "string",
          "_value": "connect"
        },
        "l0": {
          "_dirName": "l0",
          "_dirType": "string",
          "_value": "ladder"
        },
        "l1": {
          "_dirName": "l1",
          "_dirType": "string",
          "_value": "20"
        },
        "l2": {
          "_dirName": "l2",
          "_dirType": "string",
          "_value": "2"
        },
        "x": {
          "_dirName": "x",
          "_dirType": "int",
          "_value": -282
        },
        "y": {
          "_dirName": "y",
          "_dirType": "int",
          "_value": -464
        },
        "z": {
          "_dirName": "z",
          "_dirType": "int",
          "_value": 3
        },
        "f": {
          "_dirName": "f",
          "_dirType": "int",
          "_value": 1
        },
        "zM": {
          "_dirName": "zM",
          "_dirType": "int",
          "_value": 9
        }
      },
      "7": {
        "_dirName": "7",
        "_dirType": "sub",
        "oS": {
          "_dirName": "oS",
          "_dirType": "string",
          "_value": "connect"
        },
        "l0": {
          "_dirName": "l0",
          "_dirType": "string",
          "_value": "ladder"
        },
        "l1": {
          "_dirName": "l1",
          "_dirType": "string",
          "_value": "20"
        },
        "l2": {
          "_dirName": "l2",
          "_dirType": "string",
          "_value": "2"
        },
        "x": {
          "_dirName": "x",
          "_dirType": "int",
          "_value": -282
        },
        "y": {
          "_dirName": "y",
          "_dirType": "int",
          "_value": -388
        },
        "z": {
          "_dirName": "z",
          "_dirType": "int",
          "_value": 3
        },
        "f": {
          "_dirName": "f",
          "_dirType": "int",
          "_value": 1
        },
        "zM": {
          "_dirName": "zM",
          "_dirType": "int",
          "_value": 8
        }
      },
      "8": {
        "_dirName": "8",
        "_dirType": "sub",
        "oS": {
          "_dirName": "oS",
          "_dirType": "string",
          "_value": "connect"
        },
        "l0": {
          "_dirName": "l0",
          "_dirType": "string",
          "_value": "ladder"
        },
        "l1": {
          "_dirName": "l1",
          "_dirType": "string",
          "_value": "20"
        },
        "l2": {
          "_dirName": "l2",
          "_dirType": "string",
          "_value": "3"
        },
        "x": {
          "_dirName": "x",
          "_dirType": "int",
          "_value": -282
        },
        "y": {
          "_dirName": "y",
          "_dirType": "int",
          "_value": -180
        },
        "z": {
          "_dirName": "z",
          "_dirType": "int",
          "_value": 3
        },
        "f": {
          "_dirName": "f",
          "_dirType": "int",
          "_value": 1
        },
        "zM": {
          "_dirName": "zM",
          "_dirType": "int",
          "_value": 8
        }
      },
      "9": {
        "_dirName": "9",
        "_dirType": "sub",
        "oS": {
          "_dirName": "oS",
          "_dirType": "string",
          "_value": "connect"
        },
        "l0": {
          "_dirName": "l0",
          "_dirType": "string",
          "_value": "ladder"
        },
        "l1": {
          "_dirName": "l1",
          "_dirType": "string",
          "_value": "20"
        },
        "l2": {
          "_dirName": "l2",
          "_dirType": "string",
          "_value": "0"
        },
        "x": {
          "_dirName": "x",
          "_dirType": "int",
          "_value": 273
        },
        "y": {
          "_dirName": "y",
          "_dirType": "int",
          "_value": -977
        },
        "z": {
          "_dirName": "z",
          "_dirType": "int",
          "_value": 3
        },
        "f": {
          "_dirName": "f",
          "_dirType": "int",
          "_value": 0
        },
        "zM": {
          "_dirName": "zM",
          "_dirType": "int",
          "_value": 21
        }
      },
      "10": {
        "_dirName": "10",
        "_dirType": "sub",
        "oS": {
          "_dirName": "oS",
          "_dirType": "string",
          "_value": "connect"
        },
        "l0": {
          "_dirName": "l0",
          "_dirType": "string",
          "_value": "ladder"
        },
        "l1": {
          "_dirName": "l1",
          "_dirType": "string",
          "_value": "20"
        },
        "l2": {
          "_dirName": "l2",
          "_dirType": "string",
          "_value": "1"
        },
        "x": {
          "_dirName": "x",
          "_dirType": "int",
          "_value": 273
        },
        "y": {
          "_dirName": "y",
          "_dirType": "int",
          "_value": -947
        },
        "z": {
          "_dirName": "z",
          "_dirType": "int",
          "_value": 3
        },
        "f": {
          "_dirName": "f",
          "_dirType": "int",
          "_value": 0
        },
        "zM": {
          "_dirName": "zM",
          "_dirType": "int",
          "_value": 21
        }
      },
      "11": {
        "_dirName": "11",
        "_dirType": "sub",
        "oS": {
          "_dirName": "oS",
          "_dirType": "string",
          "_value": "connect"
        },
        "l0": {
          "_dirName": "l0",
          "_dirType": "string",
          "_value": "ladder"
        },
        "l1": {
          "_dirName": "l1",
          "_dirType": "string",
          "_value": "20"
        },
        "l2": {
          "_dirName": "l2",
          "_dirType": "string",
          "_value": "3"
        },
        "x": {
          "_dirName": "x",
          "_dirType": "int",
          "_value": 273
        },
        "y": {
          "_dirName": "y",
          "_dirType": "int",
          "_value": -834
        },
        "z": {
          "_dirName": "z",
          "_dirType": "int",
          "_value": 3
        },
        "f": {
          "_dirName": "f",
          "_dirType": "int",
          "_value": 0
        },
        "zM": {
          "_dirName": "zM",
          "_dirType": "int",
          "_value": 21
        }
      },
      "12": {
        "_dirName": "12",
        "_dirType": "sub",
        "oS": {
          "_dirName": "oS",
          "_dirType": "string",
          "_value": "connect"
        },
        "l2": {
          "_dirName": "l2",
          "_dirType": "string",
          "_value": "1"
        },
        "x": {
          "_dirName": "x",
          "_dirType": "int",
          "_value": 273
        },
        "y": {
          "_dirName": "y",
          "_dirType": "int",
          "_value": -909
        },
        "z": {
          "_dirName": "z",
          "_dirType": "int",
          "_value": 3
        },
        "l0": {
          "_dirName": "l0",
          "_dirType": "string",
          "_value": "ladder"
        },
        "zM": {
          "_dirName": "zM",
          "_dirType": "int",
          "_value": 21
        },
        "f": {
          "_dirName": "f",
          "_dirType": "int",
          "_value": 0
        },
        "l1": {
          "_dirName": "l1",
          "_dirType": "string",
          "_value": "20"
        }
      },
      "13": {
        "_dirName": "13",
        "_dirType": "sub",
        "zM": {
          "_dirName": "zM",
          "_dirType": "int",
          "_value": 21
        },
        "l2": {
          "_dirName": "l2",
          "_dirType": "string",
          "_value": "1"
        },
        "x": {
          "_dirName": "x",
          "_dirType": "int",
          "_value": 273
        },
        "y": {
          "_dirName": "y",
          "_dirType": "int",
          "_value": -871
        },
        "z": {
          "_dirName": "z",
          "_dirType": "int",
          "_value": 3
        },
        "l0": {
          "_dirName": "l0",
          "_dirType": "string",
          "_value": "ladder"
        },
        "f": {
          "_dirName": "f",
          "_dirType": "int",
          "_value": 0
        },
        "l1": {
          "_dirName": "l1",
          "_dirType": "string",
          "_value": "20"
        },
        "oS": {
          "_dirName": "oS",
          "_dirType": "string",
          "_value": "connect"
        }
      },
      "14": {
        "_dirName": "14",
        "_dirType": "sub",
        "oS": {
          "_dirName": "oS",
          "_dirType": "string",
          "_value": "connect"
        },
        "l2": {
          "_dirName": "l2",
          "_dirType": "string",
          "_value": "2"
        },
        "x": {
          "_dirName": "x",
          "_dirType": "int",
          "_value": -282
        },
        "y": {
          "_dirName": "y",
          "_dirType": "int",
          "_value": -312
        },
        "z": {
          "_dirName": "z",
          "_dirType": "int",
          "_value": 3
        },
        "l0": {
          "_dirName": "l0",
          "_dirType": "string",
          "_value": "ladder"
        },
        "zM": {
          "_dirName": "zM",
          "_dirType": "int",
          "_value": 8
        },
        "f": {
          "_dirName": "f",
          "_dirType": "int",
          "_value": 1
        },
        "l1": {
          "_dirName": "l1",
          "_dirType": "string",
          "_value": "20"
        }
      },
      "15": {
        "_dirName": "15",
        "_dirType": "sub",
        "zM": {
          "_dirName": "zM",
          "_dirType": "int",
          "_value": 8
        },
        "l2": {
          "_dirName": "l2",
          "_dirType": "string",
          "_value": "2"
        },
        "x": {
          "_dirName": "x",
          "_dirType": "int",
          "_value": -282
        },
        "y": {
          "_dirName": "y",
          "_dirType": "int",
          "_value": -236
        },
        "z": {
          "_dirName": "z",
          "_dirType": "int",
          "_value": 3
        },
        "l0": {
          "_dirName": "l0",
          "_dirType": "string",
          "_value": "ladder"
        },
        "f": {
          "_dirName": "f",
          "_dirType": "int",
          "_value": 1
        },
        "l1": {
          "_dirName": "l1",
          "_dirType": "string",
          "_value": "20"
        },
        "oS": {
          "_dirName": "oS",
          "_dirType": "string",
          "_value": "connect"
        }
      }
    }
  },
  "5": {
    "_dirName": "5",
    "_dirType": "sub",
    "info": {
      "_dirName": "info",
      "_dirType": "sub",
      "tS": {
        "_dirName": "tS",
        "_dirType": "string",
        "_value": "blankTower"
      },
      "tSMag": {
        "_dirName": "tSMag",
        "_dirType": "int",
        "_value": 1
      }
    },
    "tile": {
      "_dirName": "tile",
      "_dirType": "sub"
    },
    "obj": {
      "_dirName": "obj",
      "_dirType": "sub",
      "0": {
        "_dirName": "0",
        "_dirType": "sub",
        "oS": {
          "_dirName": "oS",
          "_dirType": "string",
          "_value": "insideTC"
        },
        "l0": {
          "_dirName": "l0",
          "_dirType": "string",
          "_value": "inside0"
        },
        "l1": {
          "_dirName": "l1",
          "_dirType": "string",
          "_value": "frame0"
        },
        "l2": {
          "_dirName": "l2",
          "_dirType": "string",
          "_value": "3"
        },
        "x": {
          "_dirName": "x",
          "_dirType": "int",
          "_value": -111
        },
        "y": {
          "_dirName": "y",
          "_dirType": "int",
          "_value": 325
        },
        "z": {
          "_dirName": "z",
          "_dirType": "int",
          "_value": 3
        },
        "f": {
          "_dirName": "f",
          "_dirType": "int",
          "_value": 0
        },
        "zM": {
          "_dirName": "zM",
          "_dirType": "int",
          "_value": 1
        }
      },
      "1": {
        "_dirName": "1",
        "_dirType": "sub",
        "oS": {
          "_dirName": "oS",
          "_dirType": "string",
          "_value": "insideTC"
        },
        "l0": {
          "_dirName": "l0",
          "_dirType": "string",
          "_value": "inside0"
        },
        "l1": {
          "_dirName": "l1",
          "_dirType": "string",
          "_value": "frame0"
        },
        "l2": {
          "_dirName": "l2",
          "_dirType": "string",
          "_value": "3"
        },
        "x": {
          "_dirName": "x",
          "_dirType": "int",
          "_value": -111
        },
        "y": {
          "_dirName": "y",
          "_dirType": "int",
          "_value": -445
        },
        "z": {
          "_dirName": "z",
          "_dirType": "int",
          "_value": 3
        },
        "f": {
          "_dirName": "f",
          "_dirType": "int",
          "_value": 0
        },
        "zM": {
          "_dirName": "zM",
          "_dirType": "int",
          "_value": 11
        }
      },
      "2": {
        "_dirName": "2",
        "_dirType": "sub",
        "oS": {
          "_dirName": "oS",
          "_dirType": "string",
          "_value": "connect"
        },
        "l0": {
          "_dirName": "l0",
          "_dirType": "string",
          "_value": "ladder"
        },
        "l1": {
          "_dirName": "l1",
          "_dirType": "string",
          "_value": "22"
        },
        "l2": {
          "_dirName": "l2",
          "_dirType": "string",
          "_value": "0"
        },
        "x": {
          "_dirName": "x",
          "_dirType": "int",
          "_value": 105
        },
        "y": {
          "_dirName": "y",
          "_dirType": "int",
          "_value": -916
        },
        "z": {
          "_dirName": "z",
          "_dirType": "int",
          "_value": 3
        },
        "f": {
          "_dirName": "f",
          "_dirType": "int",
          "_value": 0
        },
        "zM": {
          "_dirName": "zM",
          "_dirType": "int",
          "_value": 23
        }
      },
      "3": {
        "_dirName": "3",
        "_dirType": "sub",
        "oS": {
          "_dirName": "oS",
          "_dirType": "string",
          "_value": "connect"
        },
        "l0": {
          "_dirName": "l0",
          "_dirType": "string",
          "_value": "ladder"
        },
        "l1": {
          "_dirName": "l1",
          "_dirType": "string",
          "_value": "22"
        },
        "l2": {
          "_dirName": "l2",
          "_dirType": "string",
          "_value": "5"
        },
        "x": {
          "_dirName": "x",
          "_dirType": "int",
          "_value": 105
        },
        "y": {
          "_dirName": "y",
          "_dirType": "int",
          "_value": -866
        },
        "z": {
          "_dirName": "z",
          "_dirType": "int",
          "_value": 3
        },
        "f": {
          "_dirName": "f",
          "_dirType": "int",
          "_value": 0
        },
        "zM": {
          "_dirName": "zM",
          "_dirType": "int",
          "_value": 19
        }
      },
      "4": {
        "_dirName": "4",
        "_dirType": "sub",
        "oS": {
          "_dirName": "oS",
          "_dirType": "string",
          "_value": "connect"
        },
        "l0": {
          "_dirName": "l0",
          "_dirType": "string",
          "_value": "ladder"
        },
        "l1": {
          "_dirName": "l1",
          "_dirType": "string",
          "_value": "22"
        },
        "l2": {
          "_dirName": "l2",
          "_dirType": "string",
          "_value": "4"
        },
        "x": {
          "_dirName": "x",
          "_dirType": "int",
          "_value": 105
        },
        "y": {
          "_dirName": "y",
          "_dirType": "int",
          "_value": -809
        },
        "z": {
          "_dirName": "z",
          "_dirType": "int",
          "_value": 3
        },
        "f": {
          "_dirName": "f",
          "_dirType": "int",
          "_value": 0
        },
        "zM": {
          "_dirName": "zM",
          "_dirType": "int",
          "_value": 17
        }
      },
      "5": {
        "_dirName": "5",
        "_dirType": "sub",
        "oS": {
          "_dirName": "oS",
          "_dirType": "string",
          "_value": "connect"
        },
        "l0": {
          "_dirName": "l0",
          "_dirType": "string",
          "_value": "ladder"
        },
        "l1": {
          "_dirName": "l1",
          "_dirType": "string",
          "_value": "22"
        },
        "l2": {
          "_dirName": "l2",
          "_dirType": "string",
          "_value": "3"
        },
        "x": {
          "_dirName": "x",
          "_dirType": "int",
          "_value": 105
        },
        "y": {
          "_dirName": "y",
          "_dirType": "int",
          "_value": -696
        },
        "z": {
          "_dirName": "z",
          "_dirType": "int",
          "_value": 3
        },
        "f": {
          "_dirName": "f",
          "_dirType": "int",
          "_value": 0
        },
        "zM": {
          "_dirName": "zM",
          "_dirType": "int",
          "_value": 16
        }
      },
      "6": {
        "_dirName": "6",
        "_dirType": "sub",
        "oS": {
          "_dirName": "oS",
          "_dirType": "string",
          "_value": "connect"
        },
        "l2": {
          "_dirName": "l2",
          "_dirType": "string",
          "_value": "4"
        },
        "x": {
          "_dirName": "x",
          "_dirType": "int",
          "_value": 105
        },
        "y": {
          "_dirName": "y",
          "_dirType": "int",
          "_value": -771
        },
        "z": {
          "_dirName": "z",
          "_dirType": "int",
          "_value": 3
        },
        "l0": {
          "_dirName": "l0",
          "_dirType": "string",
          "_value": "ladder"
        },
        "zM": {
          "_dirName": "zM",
          "_dirType": "int",
          "_value": 17
        },
        "f": {
          "_dirName": "f",
          "_dirType": "int",
          "_value": 0
        },
        "l1": {
          "_dirName": "l1",
          "_dirType": "string",
          "_value": "22"
        }
      },
      "7": {
        "_dirName": "7",
        "_dirType": "sub",
        "zM": {
          "_dirName": "zM",
          "_dirType": "int",
          "_value": 17
        },
        "l2": {
          "_dirName": "l2",
          "_dirType": "string",
          "_value": "4"
        },
        "x": {
          "_dirName": "x",
          "_dirType": "int",
          "_value": 105
        },
        "y": {
          "_dirName": "y",
          "_dirType": "int",
          "_value": -733
        },
        "z": {
          "_dirName": "z",
          "_dirType": "int",
          "_value": 3
        },
        "l0": {
          "_dirName": "l0",
          "_dirType": "string",
          "_value": "ladder"
        },
        "f": {
          "_dirName": "f",
          "_dirType": "int",
          "_value": 0
        },
        "l1": {
          "_dirName": "l1",
          "_dirType": "string",
          "_value": "22"
        },
        "oS": {
          "_dirName": "oS",
          "_dirType": "string",
          "_value": "connect"
        }
      }
    }
  },
  "6": {
    "_dirName": "6",
    "_dirType": "sub",
    "info": {
      "_dirName": "info",
      "_dirType": "sub",
      "tS": {
        "_dirName": "tS",
        "_dirType": "string",
        "_value": "blankTower"
      },
      "tSMag": {
        "_dirName": "tSMag",
        "_dirType": "int",
        "_value": 1
      }
    },
    "tile": {
      "_dirName": "tile",
      "_dirType": "sub"
    },
    "obj": {
      "_dirName": "obj",
      "_dirType": "sub"
    }
  },
  "7": {
    "_dirName": "7",
    "_dirType": "sub",
    "info": {
      "_dirName": "info",
      "_dirType": "sub",
      "tS": {
        "_dirName": "tS",
        "_dirType": "string",
        "_value": "blankTower"
      },
      "tSMag": {
        "_dirName": "tSMag",
        "_dirType": "int",
        "_value": 1
      }
    },
    "tile": {
      "_dirName": "tile",
      "_dirType": "sub"
    },
    "obj": {
      "_dirName": "obj",
      "_dirType": "sub"
    }
  },
  "foothold": {
    "_dirName": "foothold",
    "_dirType": "sub",
    "1": {
      "_dirName": "1",
      "_dirType": "sub",
      "5": {
        "_dirName": "5",
        "_dirType": "sub",
        "1": {
          "_dirName": "1",
          "_dirType": "sub",
          "x1": {
            "_dirName": "x1",
            "_dirType": "int",
            "_value": -346
          },
          "y1": {
            "_dirName": "y1",
            "_dirType": "int",
            "_value": 111
          },
          "x2": {
            "_dirName": "x2",
            "_dirType": "int",
            "_value": -209
          },
          "y2": {
            "_dirName": "y2",
            "_dirType": "int",
            "_value": 111
          },
          "prev": {
            "_dirName": "prev",
            "_dirType": "int",
            "_value": 6
          },
          "next": {
            "_dirName": "next",
            "_dirType": "int",
            "_value": 0
          }
        },
        "6": {
          "_dirName": "6",
          "_dirType": "sub",
          "x1": {
            "_dirName": "x1",
            "_dirType": "int",
            "_value": -406
          },
          "y1": {
            "_dirName": "y1",
            "_dirType": "int",
            "_value": 111
          },
          "x2": {
            "_dirName": "x2",
            "_dirType": "int",
            "_value": -346
          },
          "y2": {
            "_dirName": "y2",
            "_dirType": "int",
            "_value": 111
          },
          "prev": {
            "_dirName": "prev",
            "_dirType": "int",
            "_value": 0
          },
          "next": {
            "_dirName": "next",
            "_dirType": "int",
            "_value": 1
          }
        },
        "7": {
          "_dirName": "7",
          "_dirType": "sub",
          "x1": {
            "_dirName": "x1",
            "_dirType": "int",
            "_value": -407
          },
          "y1": {
            "_dirName": "y1",
            "_dirType": "int",
            "_value": 21
          },
          "x2": {
            "_dirName": "x2",
            "_dirType": "int",
            "_value": -191
          },
          "y2": {
            "_dirName": "y2",
            "_dirType": "int",
            "_value": 21
          },
          "prev": {
            "_dirName": "prev",
            "_dirType": "int",
            "_value": 0
          },
          "next": {
            "_dirName": "next",
            "_dirType": "int",
            "_value": 0
          }
        },
        "8": {
          "_dirName": "8",
          "_dirType": "sub",
          "x1": {
            "_dirName": "x1",
            "_dirType": "int",
            "_value": -405
          },
          "y1": {
            "_dirName": "y1",
            "_dirType": "int",
            "_value": -56
          },
          "x2": {
            "_dirName": "x2",
            "_dirType": "int",
            "_value": -285
          },
          "y2": {
            "_dirName": "y2",
            "_dirType": "int",
            "_value": -56
          },
          "prev": {
            "_dirName": "prev",
            "_dirType": "int",
            "_value": 0
          },
          "next": {
            "_dirName": "next",
            "_dirType": "int",
            "_value": 10
          }
        },
        "9": {
          "_dirName": "9",
          "_dirType": "sub",
          "x1": {
            "_dirName": "x1",
            "_dirType": "int",
            "_value": -357
          },
          "y1": {
            "_dirName": "y1",
            "_dirType": "int",
            "_value": -132
          },
          "x2": {
            "_dirName": "x2",
            "_dirType": "int",
            "_value": -310
          },
          "y2": {
            "_dirName": "y2",
            "_dirType": "int",
            "_value": -132
          },
          "prev": {
            "_dirName": "prev",
            "_dirType": "int",
            "_value": 0
          },
          "next": {
            "_dirName": "next",
            "_dirType": "int",
            "_value": 19
          }
        },
        "10": {
          "_dirName": "10",
          "_dirType": "sub",
          "x1": {
            "_dirName": "x1",
            "_dirType": "int",
            "_value": -285
          },
          "y1": {
            "_dirName": "y1",
            "_dirType": "int",
            "_value": -56
          },
          "x2": {
            "_dirName": "x2",
            "_dirType": "int",
            "_value": -209
          },
          "y2": {
            "_dirName": "y2",
            "_dirType": "int",
            "_value": -56
          },
          "prev": {
            "_dirName": "prev",
            "_dirType": "int",
            "_value": 8
          },
          "next": {
            "_dirName": "next",
            "_dirType": "int",
            "_value": 0
          }
        },
        "12": {
          "_dirName": "12",
          "_dirType": "sub",
          "x1": {
            "_dirName": "x1",
            "_dirType": "int",
            "_value": -129
          },
          "y1": {
            "_dirName": "y1",
            "_dirType": "int",
            "_value": -163
          },
          "x2": {
            "_dirName": "x2",
            "_dirType": "int",
            "_value": 102
          },
          "y2": {
            "_dirName": "y2",
            "_dirType": "int",
            "_value": -163
          },
          "prev": {
            "_dirName": "prev",
            "_dirType": "int",
            "_value": 0
          },
          "next": {
            "_dirName": "next",
            "_dirType": "int",
            "_value": 0
          }
        },
        "19": {
          "_dirName": "19",
          "_dirType": "sub",
          "x1": {
            "_dirName": "x1",
            "_dirType": "int",
            "_value": -310
          },
          "y1": {
            "_dirName": "y1",
            "_dirType": "int",
            "_value": -132
          },
          "x2": {
            "_dirName": "x2",
            "_dirType": "int",
            "_value": -236
          },
          "y2": {
            "_dirName": "y2",
            "_dirType": "int",
            "_value": -132
          },
          "prev": {
            "_dirName": "prev",
            "_dirType": "int",
            "_value": 9
          },
          "next": {
            "_dirName": "next",
            "_dirType": "int",
            "_value": 0
          }
        }
      },
      "4": {
        "_dirName": "4",
        "_dirType": "sub",
        "2": {
          "_dirName": "2",
          "_dirType": "sub",
          "x1": {
            "_dirName": "x1",
            "_dirType": "int",
            "_value": 162
          },
          "y1": {
            "_dirName": "y1",
            "_dirType": "int",
            "_value": 172
          },
          "x2": {
            "_dirName": "x2",
            "_dirType": "int",
            "_value": 298
          },
          "y2": {
            "_dirName": "y2",
            "_dirType": "int",
            "_value": 172
          },
          "prev": {
            "_dirName": "prev",
            "_dirType": "int",
            "_value": 0
          },
          "next": {
            "_dirName": "next",
            "_dirType": "int",
            "_value": 0
          }
        },
        "3": {
          "_dirName": "3",
          "_dirType": "sub",
          "x1": {
            "_dirName": "x1",
            "_dirType": "int",
            "_value": 178
          },
          "y1": {
            "_dirName": "y1",
            "_dirType": "int",
            "_value": 156
          },
          "x2": {
            "_dirName": "x2",
            "_dirType": "int",
            "_value": 320
          },
          "y2": {
            "_dirName": "y2",
            "_dirType": "int",
            "_value": 156
          },
          "prev": {
            "_dirName": "prev",
            "_dirType": "int",
            "_value": 0
          },
          "next": {
            "_dirName": "next",
            "_dirType": "int",
            "_value": 0
          }
        },
        "4": {
          "_dirName": "4",
          "_dirType": "sub",
          "x1": {
            "_dirName": "x1",
            "_dirType": "int",
            "_value": 199
          },
          "y1": {
            "_dirName": "y1",
            "_dirType": "int",
            "_value": 141
          },
          "x2": {
            "_dirName": "x2",
            "_dirType": "int",
            "_value": 339
          },
          "y2": {
            "_dirName": "y2",
            "_dirType": "int",
            "_value": 141
          },
          "prev": {
            "_dirName": "prev",
            "_dirType": "int",
            "_value": 0
          },
          "next": {
            "_dirName": "next",
            "_dirType": "int",
            "_value": 0
          }
        },
        "5": {
          "_dirName": "5",
          "_dirType": "sub",
          "x1": {
            "_dirName": "x1",
            "_dirType": "int",
            "_value": 220
          },
          "y1": {
            "_dirName": "y1",
            "_dirType": "int",
            "_value": 126
          },
          "x2": {
            "_dirName": "x2",
            "_dirType": "int",
            "_value": 379
          },
          "y2": {
            "_dirName": "y2",
            "_dirType": "int",
            "_value": 126
          },
          "prev": {
            "_dirName": "prev",
            "_dirType": "int",
            "_value": 0
          },
          "next": {
            "_dirName": "next",
            "_dirType": "int",
            "_value": 0
          }
        }
      },
      "13": {
        "_dirName": "13",
        "_dirType": "sub",
        "11": {
          "_dirName": "11",
          "_dirType": "sub",
          "x1": {
            "_dirName": "x1",
            "_dirType": "int",
            "_value": -355
          },
          "y1": {
            "_dirName": "y1",
            "_dirType": "int",
            "_value": -665
          },
          "x2": {
            "_dirName": "x2",
            "_dirType": "int",
            "_value": 48
          },
          "y2": {
            "_dirName": "y2",
            "_dirType": "int",
            "_value": -665
          },
          "prev": {
            "_dirName": "prev",
            "_dirType": "int",
            "_value": 0
          },
          "next": {
            "_dirName": "next",
            "_dirType": "int",
            "_value": 0
          }
        }
      }
    },
    "2": {
      "_dirName": "2",
      "_dirType": "sub",
      "7": {
        "_dirName": "7",
        "_dirType": "sub",
        "13": {
          "_dirName": "13",
          "_dirType": "sub",
          "x1": {
            "_dirName": "x1",
            "_dirType": "int",
            "_value": 142
          },
          "y1": {
            "_dirName": "y1",
            "_dirType": "int",
            "_value": -237
          },
          "x2": {
            "_dirName": "x2",
            "_dirType": "int",
            "_value": 228
          },
          "y2": {
            "_dirName": "y2",
            "_dirType": "int",
            "_value": -237
          },
          "prev": {
            "_dirName": "prev",
            "_dirType": "int",
            "_value": 0
          },
          "next": {
            "_dirName": "next",
            "_dirType": "int",
            "_value": 0
          }
        }
      }
    },
    "3": {
      "_dirName": "3",
      "_dirType": "sub",
      "0": {
        "_dirName": "0",
        "_dirType": "sub",
        "14": {
          "_dirName": "14",
          "_dirType": "sub",
          "x1": {
            "_dirName": "x1",
            "_dirType": "int",
            "_value": -441
          },
          "y1": {
            "_dirName": "y1",
            "_dirType": "int",
            "_value": 187
          },
          "x2": {
            "_dirName": "x2",
            "_dirType": "int",
            "_value": 441
          },
          "y2": {
            "_dirName": "y2",
            "_dirType": "int",
            "_value": 187
          },
          "prev": {
            "_dirName": "prev",
            "_dirType": "int",
            "_value": 21
          },
          "next": {
            "_dirName": "next",
            "_dirType": "int",
            "_value": 20
          }
        },
        "20": {
          "_dirName": "20",
          "_dirType": "sub",
          "x1": {
            "_dirName": "x1",
            "_dirType": "int",
            "_value": 441
          },
          "y1": {
            "_dirName": "y1",
            "_dirType": "int",
            "_value": 187
          },
          "x2": {
            "_dirName": "x2",
            "_dirType": "int",
            "_value": 441
          },
          "y2": {
            "_dirName": "y2",
            "_dirType": "int",
            "_value": -7
          },
          "prev": {
            "_dirName": "prev",
            "_dirType": "int",
            "_value": 14
          },
          "next": {
            "_dirName": "next",
            "_dirType": "int",
            "_value": 0
          }
        },
        "21": {
          "_dirName": "21",
          "_dirType": "sub",
          "x1": {
            "_dirName": "x1",
            "_dirType": "int",
            "_value": -441
          },
          "y1": {
            "_dirName": "y1",
            "_dirType": "int",
            "_value": -4
          },
          "x2": {
            "_dirName": "x2",
            "_dirType": "int",
            "_value": -441
          },
          "y2": {
            "_dirName": "y2",
            "_dirType": "int",
            "_value": 187
          },
          "prev": {
            "_dirName": "prev",
            "_dirType": "int",
            "_value": 0
          },
          "next": {
            "_dirName": "next",
            "_dirType": "int",
            "_value": 14
          }
        }
      },
      "10": {
        "_dirName": "10",
        "_dirType": "sub",
        "15": {
          "_dirName": "15",
          "_dirType": "sub",
          "x1": {
            "_dirName": "x1",
            "_dirType": "int",
            "_value": -443
          },
          "y1": {
            "_dirName": "y1",
            "_dirType": "int",
            "_value": -580
          },
          "x2": {
            "_dirName": "x2",
            "_dirType": "int",
            "_value": 441
          },
          "y2": {
            "_dirName": "y2",
            "_dirType": "int",
            "_value": -580
          },
          "prev": {
            "_dirName": "prev",
            "_dirType": "int",
            "_value": 0
          },
          "next": {
            "_dirName": "next",
            "_dirType": "int",
            "_value": 0
          }
        }
      },
      "20": {
        "_dirName": "20",
        "_dirType": "sub",
        "16": {
          "_dirName": "16",
          "_dirType": "sub",
          "x1": {
            "_dirName": "x1",
            "_dirType": "int",
            "_value": 35
          },
          "y1": {
            "_dirName": "y1",
            "_dirType": "int",
            "_value": -914
          },
          "x2": {
            "_dirName": "x2",
            "_dirType": "int",
            "_value": 124
          },
          "y2": {
            "_dirName": "y2",
            "_dirType": "int",
            "_value": -914
          },
          "prev": {
            "_dirName": "prev",
            "_dirType": "int",
            "_value": 0
          },
          "next": {
            "_dirName": "next",
            "_dirType": "int",
            "_value": 0
          }
        }
      },
      "18": {
        "_dirName": "18",
        "_dirType": "sub",
        "17": {
          "_dirName": "17",
          "_dirType": "sub",
          "x1": {
            "_dirName": "x1",
            "_dirType": "int",
            "_value": 144
          },
          "y1": {
            "_dirName": "y1",
            "_dirType": "int",
            "_value": -841
          },
          "x2": {
            "_dirName": "x2",
            "_dirType": "int",
            "_value": 233
          },
          "y2": {
            "_dirName": "y2",
            "_dirType": "int",
            "_value": -841
          },
          "prev": {
            "_dirName": "prev",
            "_dirType": "int",
            "_value": 0
          },
          "next": {
            "_dirName": "next",
            "_dirType": "int",
            "_value": 0
          }
        }
      },
      "22": {
        "_dirName": "22",
        "_dirType": "sub",
        "18": {
          "_dirName": "18",
          "_dirType": "sub",
          "x1": {
            "_dirName": "x1",
            "_dirType": "int",
            "_value": 175
          },
          "y1": {
            "_dirName": "y1",
            "_dirType": "int",
            "_value": -975
          },
          "x2": {
            "_dirName": "x2",
            "_dirType": "int",
            "_value": 390
          },
          "y2": {
            "_dirName": "y2",
            "_dirType": "int",
            "_value": -975
          },
          "prev": {
            "_dirName": "prev",
            "_dirType": "int",
            "_value": 0
          },
          "next": {
            "_dirName": "next",
            "_dirType": "int",
            "_value": 0
          }
        }
      }
    }
  },
  "ladderRope": {
    "_dirName": "ladderRope",
    "_dirType": "sub",
    "1": {
      "_dirName": "1",
      "_dirType": "sub",
      "l": {
        "_dirName": "l",
        "_dirType": "int",
        "_value": 1
      },
      "uf": {
        "_dirName": "uf",
        "_dirType": "int",
        "_value": 1
      },
      "x": {
        "_dirName": "x",
        "_dirType": "int",
        "_value": -281
      },
      "y1": {
        "_dirName": "y1",
        "_dirType": "int",
        "_value": -579
      },
      "y2": {
        "_dirName": "y2",
        "_dirType": "int",
        "_value": -175
      },
      "page": {
        "_dirName": "page",
        "_dirType": "int",
        "_value": 4
      }
    },
    "2": {
      "_dirName": "2",
      "_dirType": "sub",
      "l": {
        "_dirName": "l",
        "_dirType": "int",
        "_value": 1
      },
      "uf": {
        "_dirName": "uf",
        "_dirType": "int",
        "_value": 1
      },
      "x": {
        "_dirName": "x",
        "_dirType": "int",
        "_value": 105
      },
      "y1": {
        "_dirName": "y1",
        "_dirType": "int",
        "_value": -913
      },
      "y2": {
        "_dirName": "y2",
        "_dirType": "int",
        "_value": -690
      },
      "page": {
        "_dirName": "page",
        "_dirType": "int",
        "_value": 4
      }
    },
    "3": {
      "_dirName": "3",
      "_dirType": "sub",
      "l": {
        "_dirName": "l",
        "_dirType": "int",
        "_value": 1
      },
      "uf": {
        "_dirName": "uf",
        "_dirType": "int",
        "_value": 1
      },
      "x": {
        "_dirName": "x",
        "_dirType": "int",
        "_value": 272
      },
      "y1": {
        "_dirName": "y1",
        "_dirType": "int",
        "_value": -974
      },
      "y2": {
        "_dirName": "y2",
        "_dirType": "int",
        "_value": -826
      },
      "page": {
        "_dirName": "page",
        "_dirType": "int",
        "_value": 5
      }
    }
  },
  "miniMap": {
    "_dirName": "miniMap",
    "_dirType": "sub",
    "canvas": {
      "_dirName": "canvas",
      "_dirType": "canvas",
      "_width": 70,
      "_height": 112
    },
    "width": {
      "_dirName": "width",
      "_dirType": "int",
      "_value": 1122
    },
    "height": {
      "_dirName": "height",
      "_dirType": "int",
      "_value": 1800
    },
    "centerX": {
      "_dirName": "centerX",
      "_dirType": "int",
      "_value": 562
    },
    "centerY": {
      "_dirName": "centerY",
      "_dirType": "int",
      "_value": 1355
    },
    "mag": {
      "_dirName": "mag",
      "_dirType": "int",
      "_value": 4
    }
  },
  "portal": {
    "_dirName": "portal",
    "_dirType": "sub",
    "0": {
      "_dirName": "0",
      "_dirType": "sub",
      "pn": {
        "_dirName": "pn",
        "_dirType": "string",
        "_value": "sp"
      },
      "pt": {
        "_dirName": "pt",
        "_dirType": "int",
        "_value": 0
      },
      "x": {
        "_dirName": "x",
        "_dirType": "int",
        "_value": 31
      },
      "y": {
        "_dirName": "y",
        "_dirType": "int",
        "_value": 68
      },
      "tm": {
        "_dirName": "tm",
        "_dirType": "int",
        "_value": 999999999
      },
      "tn": {
        "_dirName": "tn",
        "_dirType": "string",
        "_value": ""
      }
    },
    "1": {
      "_dirName": "1",
      "_dirType": "sub",
      "pn": {
        "_dirName": "pn",
        "_dirType": "string",
        "_value": "sp"
      },
      "pt": {
        "_dirName": "pt",
        "_dirType": "int",
        "_value": 0
      },
      "x": {
        "_dirName": "x",
        "_dirType": "int",
        "_value": -273
      },
      "y": {
        "_dirName": "y",
        "_dirType": "int",
        "_value": -49
      },
      "tm": {
        "_dirName": "tm",
        "_dirType": "int",
        "_value": 999999999
      },
      "tn": {
        "_dirName": "tn",
        "_dirType": "string",
        "_value": ""
      }
    },
    "2": {
      "_dirName": "2",
      "_dirType": "sub",
      "pn": {
        "_dirName": "pn",
        "_dirType": "string",
        "_value": "out00"
      },
      "pt": {
        "_dirName": "pt",
        "_dirType": "int",
        "_value": 2
      },
      "x": {
        "_dirName": "x",
        "_dirType": "int",
        "_value": 308
      },
      "y": {
        "_dirName": "y",
        "_dirType": "int",
        "_value": 126
      },
      "tm": {
        "_dirName": "tm",
        "_dirType": "int",
        "_value": 220000300
      },
      "tn": {
        "_dirName": "tn",
        "_dirType": "string",
        "_value": "in05"
      },
      "script": {
        "_dirName": "script",
        "_dirType": "string",
        "_value": ""
      }
    }
  }
}
